gnn/GNN.py
gnn/__init__.py
gnn/gnn_utils.py
gnn/load.py
gnn-1.1.9.dist-info/LICENSE
gnn-1.1.9.dist-info/METADATA
gnn-1.1.9.dist-info/WHEEL
gnn-1.1.9.dist-info/top_level.txt
gnn-1.1.9.dist-info/RECORD
