Metadata-Version: 2.1
Name: gnn
Version: 1.1.9
Summary: Graph Neural Network Tensorflow implementation
Home-page: https://github.com/mtiezzi/gnn
Author: Matteo Tiezzi
Author-email: mtiezzi@diism.unisi.it
License: UNKNOWN
Platform: UNKNOWN
Classifier: Programming Language :: Python :: 3
Classifier: License :: OSI Approved :: BSD License
Classifier: Operating System :: OS Independent
